[[{"Full_Name": "Lance, Leonard", "SponsorDescription": " as Primary Sponsor", "BioLink": null}, {"Full_Name": "Codey, Richard J.", "SponsorDescription": " as Primary Sponsor", "BioLink": null}], [{"Full_Name": "Bennett, John O.", "SponsorDescription": " as Co-Sponsor", "BioLink": null}, {"Full_Name": "Allen, Diane B.", "SponsorDescription": " as Co-Sponsor", "BioLink": null}, {"Full_Name": "Kenny, Bernard F., Jr.", "SponsorDescription": " as Co-Sponsor", "BioLink": null}, {"Full_Name": "Bark, Martha W.", "SponsorDescription": " as Co-Sponsor", "BioLink": null}, {"Full_Name": "Connors, Leonard T., Jr.", "SponsorDescription": " as Co-Sponsor", "BioLink": null}, {"Full_Name": "Ciesla, Andrew R.", "SponsorDescription": " as Co-Sponsor", "BioLink": null}, {"Full_Name": "Littell, Robert E.", "SponsorDescription": " as Co-Sponsor", "BioLink": null}, {"Full_Name": "Martin, Robert J.", "SponsorDescription": " as Co-Sponsor", "BioLink": null}, {"Full_Name": "Bucco, Anthony R.", "SponsorDescription": " as Co-Sponsor", "BioLink": null}, {"Full_Name": "Inverso, Peter A.", "SponsorDescription": " as Co-Sponsor", "BioLink": null}, {"Full_Name": "Singer, Robert W.", "SponsorDescription": " as Co-Sponsor", "BioLink": "/legislative-roster/93/senator-singer"}, {"Full_Name": "Turner, Shirley K.", "SponsorDescription": " as Co-Sponsor", "BioLink": "/legislative-roster/47/senator-turner"}, {"Full_Name": "Charles, Joseph, Jr.", "SponsorDescription": " as Co-Sponsor", "BioLink": null}, {"Full_Name": "James, Sharpe", "SponsorDescription": " as Co-Sponsor", "BioLink": null}, {"Full_Name": "Vitale, Joseph F.", "SponsorDescription": " as Co-Sponsor", "BioLink": "/legislative-roster/175/senator-vitale"}, {"Full_Name": "Smith, Bob", "SponsorDescription": " as Co-Sponsor", "BioLink": "/legislative-roster/53/senator-smith"}, {"Full_Name": "Cafiero, James S.", "SponsorDescription": " as Co-Sponsor", "BioLink": null}, {"Full_Name": "Palaia, Joseph A.", "SponsorDescription": " as Co-Sponsor", "BioLink": null}, {"Full_Name": "Gill, Nia H., Esq.", "SponsorDescription": " as Co-Sponsor", "BioLink": null}, {"Full_Name": "Sacco, Nicholas J.", "SponsorDescription": " as Co-Sponsor", "BioLink": null}, {"Full_Name": "Sweeney, Stephen M.", "SponsorDescription": " as Co-Sponsor", "BioLink": null}, {"Full_Name": "Suliga, Joseph", "SponsorDescription": " as Co-Sponsor", "BioLink": null}, {"Full_Name": "Girgenti, John A.", "SponsorDescription": " as Co-Sponsor", "BioLink": null}, {"Full_Name": "Lesniak, Raymond J.", "SponsorDescription": " as Co-Sponsor", "BioLink": null}, {"Full_Name": "Kyrillos, Joseph M., Jr.", "SponsorDescription": " as Co-Sponsor", "BioLink": null}, {"Full_Name": "Rice, Ronald L.", "SponsorDescription": " as Co-Sponsor", "BioLink": null}, {"Full_Name": "Matheussen, John J.", "SponsorDescription": " as Co-Sponsor", "BioLink": null}, {"Full_Name": "Coniglio, Joseph", "SponsorDescription": " as Co-Sponsor", "BioLink": null}, {"Full_Name": "Kavanaugh, Walter J.", "SponsorDescription": " as Co-Sponsor", "BioLink": null}]]