[[{"Full_Name": "Lynch, John A.", "SponsorDescription": " as Primary Sponsor", "BioLink": null}, {"Full_Name": "Sinagra, Jack", "SponsorDescription": " as Primary Sponsor", "BioLink": null}], [{"Full_Name": "Matheussen, John J.", "SponsorDescription": " as Co-Sponsor", "BioLink": null}, {"Full_Name": "Vitale, Joseph F.", "SponsorDescription": " as Co-Sponsor", "BioLink": "/legislative-roster/175/senator-vitale"}, {"Full_Name": "Cottrell, Melvin", "SponsorDescription": " as Co-Sponsor", "BioLink": null}]]