[[{"Full_Name": "Timberlake, Britnee N.", "SponsorDescription": " as Primary Sponsor", "BioLink": "/legislative-roster/490/senator-timberlake"}, {"Full_Name": "McKnight, Angela V.", "SponsorDescription": " as Primary Sponsor", "BioLink": "/legislative-roster/483/senator-mcknight"}], [{"Full_Name": "McKeon, John F.", "SponsorDescription": " as Co-Sponsor", "BioLink": "/legislative-roster/478/senator-mckeon"}, {"Full_Name": "Bramnick, Jon M.", "SponsorDescription": " as Co-Sponsor", "BioLink": "/legislative-roster/433/senator-bramnick"}]]