[[{"Full_Name": "Durr, Edward", "SponsorDescription": " as Primary Sponsor", "BioLink": null}, {"Full_Name": "Singer, Robert W.", "SponsorDescription": " as Primary Sponsor", "BioLink": "/legislative-roster/93/senator-singer"}], [{"Full_Name": "Corrado, Kristin M.", "SponsorDescription": " as Co-Sponsor", "BioLink": "/legislative-roster/392/senator-corrado"}, {"Full_Name": "Oroho, Steven V.", "SponsorDescription": " as Co-Sponsor", "BioLink": null}, {"Full_Name": "Pennacchio, Joseph", "SponsorDescription": " as Co-Sponsor", "BioLink": "/legislative-roster/305/senator-pennacchio"}, {"Full_Name": "Stanfield, Jean", "SponsorDescription": " as Co-Sponsor", "BioLink": null}]]